foliant/preprocessors/badges.py
foliantcontrib.badges-1.0.4.dist-info/LICENSE
foliantcontrib.badges-1.0.4.dist-info/METADATA
foliantcontrib.badges-1.0.4.dist-info/WHEEL
foliantcontrib.badges-1.0.4.dist-info/top_level.txt
foliantcontrib.badges-1.0.4.dist-info/RECORD
